Metadata-Version: 2.1
Name: copydeps
Version: 1.1.0
Summary: Copy dependencies required by a Linux executable.
Home-page: https://github.com/genymobile/copydeps
Author: Genymobile
Author-email: opensource@genymobile.com
License: Apache 2.0
Platform: Linux
Classifier: Development Status :: 5 - Production/Stable
Classifier: Environment :: Console
Classifier: Intended Audience :: Developers
Classifier: License :: OSI Approved :: Apache Software License
Classifier: Operating System :: POSIX :: Linux
Classifier: Programming Language :: Python :: 3
Classifier: Topic :: Software Development :: Build Tools
